django_bulk_load/__init__.py
django_bulk_load/bulk_load.py
django_bulk_load/django.py
django_bulk_load/queries.py
django_bulk_load/utils.py
django_bulk_load-1.4.3.dist-info/LICENSE
django_bulk_load-1.4.3.dist-info/METADATA
django_bulk_load-1.4.3.dist-info/WHEEL
django_bulk_load-1.4.3.dist-info/top_level.txt
django_bulk_load-1.4.3.dist-info/RECORD
