Metadata-Version: 2.1
Name: django-bulk-load
Version: 1.4.3
Summary: Bulk load Django models
Home-page: https://github.com/cedar-team/django-bulk-load
Author: Cedar
Author-email: support@cedar.com
License: MIT
Classifier: Programming Language :: Python :: 3
Classifier: License :: OSI Approved :: MIT License
Classifier: Operating System :: OS Independent
Requires-Python: >=3.6
License-File: LICENSE
Requires-Dist: django >=2.2
Requires-Dist: psycopg2 >=2.8.6
Provides-Extra: test
